x509_toolkit/__init__.py
x509_toolkit/requirements.txt
x509_toolkit/x509_toolkit.py
x509_toolkit-0.0.1.dist-info/LICENSE
x509_toolkit-0.0.1.dist-info/METADATA
x509_toolkit-0.0.1.dist-info/WHEEL
x509_toolkit-0.0.1.dist-info/RECORD
