Metadata-Version: 2.1
Name: x509-toolkit
Version: 0.0.1
Summary: A Python library for parsing and normalizing X.509 certificates in Base64 DER format. It extracts key details like serial number, subject DN, issuer DN, and validity periods, with support for consistent DN normalization.
License: MIT
Author: Michael Mohamed
Author-email: michaelm063089@gmail.com
Requires-Python: >=3.9, !=2.7.*, !=3.0.*, !=3.1.*, !=3.2.*, !=3.3.*, !=3.4.*, !=3.5.*, !=3.6.*, !=3.7.*, !=3.8.*
Classifier: License :: OSI Approved :: MIT License
Classifier: Programming Language :: Python :: 3
Classifier: Programming Language :: Python :: 3.10
Classifier: Programming Language :: Python :: 3.11
Classifier: Programming Language :: Python :: 3.12
Classifier: Programming Language :: Python :: 3.13
Requires-Dist: cryptography (>=44.0.0,<45.0.0)
